kutils/__init__.py
kutils/dicts.py
kutils/stats.py
kutils-0.3.0.dist-info/DESCRIPTION.rst
kutils-0.3.0.dist-info/METADATA
kutils-0.3.0.dist-info/RECORD
kutils-0.3.0.dist-info/WHEEL
kutils-0.3.0.dist-info/metadata.json
kutils-0.3.0.dist-info/top_level.txt
