Metadata-Version: 2.0
Name: kutils
Version: 0.3.0
Summary: Kyle's utilities
Home-page: https://github.com/kisom/pykutils
Author: K. Isom
Author-email: kyle@imap.cc
License: Copyright (c) 2017 Kyle Isom <kyle@imap.cc>
